<?xml version="1.0" encoding="UTF-8" ?>
<OpenSearchDescription xmlns="http://a9.com/-/spec/opensearch/1.1/">
  <ShortName>Annuaire Polytechnique.org</ShortName>
  <Description>Recherche rapide dans l'annuaire de Polytechnique.org</Description>
  <Tags>polytechnique alumni</Tags>
  <Contact>contact@polytechnique.org</Contact>
  <Url type="text/html" template="https://www.polytechnique.org/search?quick={searchTerms}" />
  <Language>fr_FR</Language>
  <OutputEncoding>UTF-8</OutputEncoding>
  <InputEncoding>UTF-8</InputEncoding>
</OpenSearchDescription>
